cli_forge/__init__.py
cli_forge/cli_forge.py
cli_forge-0.0.4.dist-info/METADATA
cli_forge-0.0.4.dist-info/WHEEL
cli_forge-0.0.4.dist-info/licenses/LICENSE
cli_forge-0.0.4.dist-info/RECORD
