Metadata-Version: 2.1
Name: cli-forge
Version: 0.0.4
Summary: A tool for building simple CLIs
Project-URL: Homepage, https://github.com/JmThrCreator/cli-forge
Project-URL: Bug Tracker, https://github.com/JmThrCreator/cli-forge/issues
Author-email: Jonathan <jonathanfmaggio@gmail.com>
License-File: LICENSE
Classifier: License :: OSI Approved :: MIT License
Classifier: Operating System :: OS Independent
Classifier: Programming Language :: Python :: 3
Requires-Python: >=3.7
Requires-Dist: windows-curses; os_name == 'nt'
